memsim/__init__.py
memsim/__version__.py
memsim/__pycache__/__init__.cpython-39.pyc
memsim/__pycache__/__version__.cpython-39.pyc
memsim/__pycache__/membrane.cpython-39.pyc
memsim/config/__colors__.py
memsim/config/__config__.py
memsim/config/__disp__.py
memsim/config/memsim.json
memsim/config/__pycache__/__colors__.cpython-39.pyc
memsim/config/__pycache__/__config__.cpython-39.pyc
memsim/config/__pycache__/__disp__.cpython-39.pyc
memsim/membrane/__init__.py
memsim/membrane/membrane.py
memsim/membrane/__pycache__/__init__.cpython-39.pyc
memsim/membrane/__pycache__/membrane.cpython-39.pyc
memsim-0.0.1.dist-info/LICENSE.txt
memsim-0.0.1.dist-info/METADATA
memsim-0.0.1.dist-info/WHEEL
memsim-0.0.1.dist-info/top_level.txt
memsim-0.0.1.dist-info/RECORD
